leventools/__init__.py
leventools/data_science/__init__.py
leventools/data_science/eda.py
leventools/data_science/eval.py
leventools/data_science/stats.py
leventools/tools/__init__.py
leventools/tools/analyzer.py
leventools/tools/file_handling.py
leventools/tools/utils.py
leventools-0.1.3.dist-info/LICENSE
leventools-0.1.3.dist-info/METADATA
leventools-0.1.3.dist-info/WHEEL
leventools-0.1.3.dist-info/top_level.txt
leventools-0.1.3.dist-info/RECORD
